swipe/__init__.py
swipe-0.0.6.dist-info/LICENSE
swipe-0.0.6.dist-info/METADATA
swipe-0.0.6.dist-info/WHEEL
swipe-0.0.6.dist-info/top_level.txt
swipe-0.0.6.dist-info/RECORD
