Metadata-Version: 2.1
Name: swipe
Version: 0.0.6
Summary: Swipe through data once with a comb that will pick up the points you're looking for.
Home-page: https://github.com/thorwhalen/swipe
Author: Thor Whalen
License: UNKNOWN
Keywords: data,search
Platform: any
License-File: LICENSE
